palm_pytorch/__init__.py
palm_pytorch/autoregressive_wrapper.py
palm_pytorch/palm_lite.py
palm_pytorch/palm_pytorch.py
palm_pytorch/triton/__init__.py
palm_pytorch/triton/layernorm.py
palm_pytorch/triton/palm.py
palm_pytorch/triton/softmax.py
PaLM_pytorch-0.2.2.dist-info/LICENSE
PaLM_pytorch-0.2.2.dist-info/METADATA
PaLM_pytorch-0.2.2.dist-info/WHEEL
PaLM_pytorch-0.2.2.dist-info/top_level.txt
PaLM_pytorch-0.2.2.dist-info/RECORD
